app/__init__.py
app/bootstrap.py
app/intent_app.py
app/middleware.py
app/settings.py
app/celery/__init__.py
app/celery/celery_app.py
app/celery/tasks.py
app/graph/__init__.py
app/tools/__init__.py
app/tools/async_calculator_add.py
core/__init__.py
core/base/__init__.py
core/base/component.py
core/base/constants.py
core/base/graph.py
core/base/job.py
core/base/runnable.py
core/base/schema.py
core/base/team.py
core/base/workflow.py
core/graph/__init__.py
core/graph/tool_call_async_interrupt_graph.py
core/graph/tool_call_interrupt_graph.py
core/graph/tool_call_ws_interrupt_graph.py
core/manager/__init__.py
core/manager/router/__init__.py
core/manager/router/schema.py
core/manager/router/utils.py
core/manager/task/__init__.py
core/manager/tool/__init__.py
core/manager/tool/base.py
core/manager/tool/flat_toolkit_manager.py
core/manager/tool/ws_toolkit_manager.py
core/manager/workflow/__init__.py
core/manager/workflow/node_manager.py
core/pattern/__init__.py
core/pattern/schema.py
core/pattern/component/__init__.py
core/pattern/component/executor/__init__.py
core/pattern/component/executor/base.py
core/pattern/component/executor/schema.py
core/pattern/component/executor/sequence_executor.py
core/pattern/component/executor/step_executor.py
core/pattern/component/planner/__init__.py
core/pattern/component/planner/base.py
core/pattern/component/planner/cot_planner.py
core/pattern/component/planner/cot_replanner.py
core/pattern/component/planner/dag_planner.py
core/pattern/component/planner/dag_replanner.py
core/pattern/component/planner/first_step_planner.py
core/pattern/component/planner/parser.py
core/pattern/component/planner/schema.py
core/pattern/component/planner/sequence_planner.py
core/pattern/component/resolver/__init__.py
core/pattern/component/resolver/base.py
core/pattern/component/resolver/schema.py
core/pattern/component/resolver/summary_resolver.py
core/pattern/component/utils/__init__.py
core/pattern/component/utils/tools.py
core/pattern/llm_call/__init__.py
agentic_kit-0.0.1.dist-info/METADATA
agentic_kit-0.0.1.dist-info/WHEEL
agentic_kit-0.0.1.dist-info/top_level.txt
agentic_kit-0.0.1.dist-info/RECORD
