Metadata-Version: 2.2
Name: agentic-kit
Version: 0.0.1
Summary: EDA agent framework based on Langgraph
Home-page: 
Author: manson
Author-email: manson.li3307@gmail.com
Keywords: AI,LLM,Agent
Classifier: Development Status :: 4 - Beta
Classifier: Intended Audience :: Developers
Classifier: Topic :: Scientific/Engineering :: Artificial Intelligence
Classifier: Programming Language :: Python :: 3
Classifier: License :: OSI Approved :: Apache Software License
Classifier: Operating System :: OS Independent
Requires-Python: >=3.10
Requires-Dist: langgraph==0.1.19
Requires-Dist: langchain==0.2.12
Requires-Dist: langchain-openai==0.1.20
Requires-Dist: pandas>=2.2.2
Requires-Dist: grandalf
Dynamic: author
Dynamic: author-email
Dynamic: classifier
Dynamic: description
Dynamic: description-content-type
Dynamic: keywords
Dynamic: requires-dist
Dynamic: requires-python
Dynamic: summary
